odoo/addons/account_invoice_tier_validation_approver/README.rst
odoo/addons/account_invoice_tier_validation_approver/__init__.py
odoo/addons/account_invoice_tier_validation_approver/__manifest__.py
odoo/addons/account_invoice_tier_validation_approver/i18n/account_invoice_tier_validation_approver.pot
odoo/addons/account_invoice_tier_validation_approver/models/__init__.py
odoo/addons/account_invoice_tier_validation_approver/models/account_invoice.py
odoo/addons/account_invoice_tier_validation_approver/models/res_company.py
odoo/addons/account_invoice_tier_validation_approver/models/res_config_settings.py
odoo/addons/account_invoice_tier_validation_approver/models/res_partner.py
odoo/addons/account_invoice_tier_validation_approver/readme/CONFIGURE.rst
odoo/addons/account_invoice_tier_validation_approver/readme/CONTRIBUTORS.rst
odoo/addons/account_invoice_tier_validation_approver/readme/DESCRIPTION.rst
odoo/addons/account_invoice_tier_validation_approver/readme/USAGE.rst
odoo/addons/account_invoice_tier_validation_approver/static/description/icon.png
odoo/addons/account_invoice_tier_validation_approver/static/description/index.html
odoo/addons/account_invoice_tier_validation_approver/tests/__init__.py
odoo/addons/account_invoice_tier_validation_approver/tests/test_account_invoice_tier_validation_approver.py
odoo/addons/account_invoice_tier_validation_approver/views/account_invoice_views.xml
odoo/addons/account_invoice_tier_validation_approver/views/res_config_settings_views.xml
odoo/addons/account_invoice_tier_validation_approver/views/res_partner_views.xml
odoo12_addon_account_invoice_tier_validation_approver-12.0.1.0.1.dist-info/METADATA
odoo12_addon_account_invoice_tier_validation_approver-12.0.1.0.1.dist-info/WHEEL
odoo12_addon_account_invoice_tier_validation_approver-12.0.1.0.1.dist-info/top_level.txt
odoo12_addon_account_invoice_tier_validation_approver-12.0.1.0.1.dist-info/RECORD
